{
  "generated_at_utc": "2026-07-14T18:35:07.396339+00:00",
  "symbol": "MUUSDT",
  "interval_minutes": 5,
  "latest_candle": {
    "time_utc": "2026-07-14T18:30:00+00:00",
    "start_time_ms": 1784053800000,
    "close": 983.25
  },
  "signal_log": {
    "signal_id": 55,
    "model_version": "pattern_scanner_v2_2"
  },
  "history": {
    "total_feature_rows": 3483,
    "completed_outcome_rows": 3435,
    "similar_cases_used": 50,
    "average_similarity_pct": 13.827,
    "best_similarity_pct": 19.436,
    "purge_gap_bars": 48,
    "purge_gap_minutes": 240
  },
  "feature_quality": {
    "selected_feature_count": 41,
    "selected_features": [
      "return_1",
      "return_3",
      "return_12",
      "ema20_dist",
      "ema50_dist",
      "ema200_dist",
      "rsi14",
      "atr_pct",
      "macd",
      "macd_signal",
      "macd_hist",
      "bb_pos",
      "volume_ratio",
      "range_pct",
      "body_pct",
      "adx14",
      "bb_width",
      "upper_wick_pct",
      "lower_wick_pct",
      "vwap20_dist",
      "btc_return_1",
      "btc_return_3",
      "btc_return_12",
      "btc_ema20_dist",
      "eth_return_1",
      "eth_return_3",
      "eth_return_12",
      "eth_ema20_dist",
      "rel_btc_return_1",
      "rel_btc_return_3",
      "rel_btc_return_12",
      "rel_eth_return_12",
      "snapshot_available",
      "bos_up_20",
      "bos_down_20",
      "liquidity_sweep_high_20",
      "liquidity_sweep_low_20",
      "fvg_up",
      "fvg_down",
      "fvg_up_gap_pct",
      "fvg_down_gap_pct"
    ],
    "skipped_features": {
      "snap_spread_pct": "too_few_history_values_162",
      "snap_price_24h_pct": "too_few_history_values_162",
      "snap_funding_rate": "too_few_history_values_162",
      "snap_oi_change_pct": "too_few_history_values_162",
      "snap_long_short_ratio": "too_few_history_values_162",
      "snap_long_ratio_change": "too_few_history_values_162",
      "snap_taker_delta_ratio": "too_few_history_values_162",
      "snap_book_imbalance_top10": "too_few_history_values_162",
      "snap_book_imbalance_top25": "too_few_history_values_162",
      "snap_notional_imbalance_top10": "too_few_history_values_162"
    },
    "minimum_required_feature_count": 8
  },
  "pattern_model": {
    "model_type": "nearest_neighbor_pattern_v2_2",
    "signal": "BULLISH",
    "confidence_0_10": 3.89,
    "decision": {
      "side": "LONG",
      "worth_trading": false,
      "reliability_grade": "B",
      "long_winrate_4h_pct": 58.0,
      "short_winrate_4h_pct": 42.0,
      "avg_4h_pct": 0.10917,
      "median_4h_pct": 0.17694,
      "long_tp1_before_sl_4h_all_cases_pct": 30.0,
      "short_tp1_before_sl_4h_all_cases_pct": 46.0,
      "reason": "LONG pusė turi istorinį pranašumą: cases=50, winrate=58.0%, avg_side_return=0.1092%, TP1_before_SL=30.0%, grade=B."
    },
    "probabilities": {
      "long_15m_pct": 50.0,
      "short_15m_pct": 50.0,
      "long_1h_pct": 52.0,
      "short_1h_pct": 48.0,
      "long_4h_pct": 58.0,
      "short_4h_pct": 42.0
    },
    "expected_returns": {
      "average_15m_pct": -0.09327,
      "median_15m_pct": -0.01074,
      "average_1h_pct": -0.02013,
      "median_1h_pct": 0.05099,
      "average_4h_pct": 0.10917,
      "median_4h_pct": 0.17694,
      "best_4h_pct": 4.7474,
      "worst_4h_pct": -4.49104
    },
    "outcome_stats": {
      "cases": 50,
      "direction": {
        "15m": {
          "valid_cases": 50,
          "long_winrate_pct": 50.0,
          "short_winrate_pct": 50.0,
          "flat_cases_pct": 0.0
        },
        "1h": {
          "valid_cases": 50,
          "long_winrate_pct": 52.0,
          "short_winrate_pct": 48.0,
          "flat_cases_pct": 0.0
        },
        "4h": {
          "valid_cases": 50,
          "long_winrate_pct": 58.0,
          "short_winrate_pct": 42.0,
          "flat_cases_pct": 0.0
        }
      },
      "returns": {
        "15m": {
          "average_pct": -0.09327,
          "median_pct": -0.01074,
          "best_pct": 1.11841,
          "worst_pct": -3.06233
        },
        "1h": {
          "average_pct": -0.02013,
          "median_pct": 0.05099,
          "best_pct": 4.01271,
          "worst_pct": -3.39594
        },
        "4h": {
          "average_pct": 0.10917,
          "median_pct": 0.17694,
          "best_pct": 4.7474,
          "worst_pct": -4.49104
        }
      },
      "risk": {
        "15m": {
          "long_avg_mfe_pct": 0.23587,
          "long_avg_mae_pct": -0.36463,
          "long_median_mfe_pct": 0.14276,
          "long_median_mae_pct": -0.21048,
          "short_avg_mfe_pct": 0.36463,
          "short_avg_mae_pct": 0.23587
        },
        "1h": {
          "long_avg_mfe_pct": 0.62166,
          "long_avg_mae_pct": -0.73503,
          "long_median_mfe_pct": 0.30412,
          "long_median_mae_pct": -0.27635,
          "short_avg_mfe_pct": 0.73503,
          "short_avg_mae_pct": 0.62166
        },
        "4h": {
          "long_avg_mfe_pct": 1.36879,
          "long_avg_mae_pct": -1.42094,
          "long_median_mfe_pct": 0.64981,
          "long_median_mae_pct": -1.08245,
          "short_avg_mfe_pct": 1.42094,
          "short_avg_mae_pct": 1.36879
        }
      },
      "tp_sl": {
        "long_tp1_before_sl_15m": {
          "available": true,
          "valid_sequence_cases": 2,
          "success_all_cases_pct": 2.0,
          "success_when_decided_pct": 50.0
        },
        "long_tp2_before_sl_15m": {
          "available": true,
          "valid_sequence_cases": 1,
          "success_all_cases_pct": 0.0,
          "success_when_decided_pct": 0.0
        },
        "short_tp1_before_sl_15m": {
          "available": true,
          "valid_sequence_cases": 4,
          "success_all_cases_pct": 8.0,
          "success_when_decided_pct": 100.0
        },
        "short_tp2_before_sl_15m": {
          "available": true,
          "valid_sequence_cases": 1,
          "success_all_cases_pct": 2.0,
          "success_when_decided_pct": 100.0
        },
        "long_tp1_before_sl_1h": {
          "available": true,
          "valid_sequence_cases": 15,
          "success_all_cases_pct": 16.0,
          "success_when_decided_pct": 53.33
        },
        "long_tp2_before_sl_1h": {
          "available": true,
          "valid_sequence_cases": 11,
          "success_all_cases_pct": 8.0,
          "success_when_decided_pct": 36.36
        },
        "short_tp1_before_sl_1h": {
          "available": true,
          "valid_sequence_cases": 23,
          "success_all_cases_pct": 34.0,
          "success_when_decided_pct": 73.91
        },
        "short_tp2_before_sl_1h": {
          "available": true,
          "valid_sequence_cases": 11,
          "success_all_cases_pct": 10.0,
          "success_when_decided_pct": 45.45
        },
        "long_tp1_before_sl_4h": {
          "available": true,
          "valid_sequence_cases": 31,
          "success_all_cases_pct": 30.0,
          "success_when_decided_pct": 48.39
        },
        "long_tp2_before_sl_4h": {
          "available": true,
          "valid_sequence_cases": 26,
          "success_all_cases_pct": 18.0,
          "success_when_decided_pct": 34.62
        },
        "short_tp1_before_sl_4h": {
          "available": true,
          "valid_sequence_cases": 31,
          "success_all_cases_pct": 46.0,
          "success_when_decided_pct": 74.19
        },
        "short_tp2_before_sl_4h": {
          "available": true,
          "valid_sequence_cases": 23,
          "success_all_cases_pct": 24.0,
          "success_when_decided_pct": 52.17
        }
      }
    }
  },
  "condition_model": {
    "model_type": "bucket_condition_stats_v2_2",
    "available": true,
    "match_strength": "target_reached",
    "used_columns": [
      "trend_regime",
      "rsi_bucket",
      "btc_regime"
    ],
    "latest_values": {
      "trend_regime": "pullback_above_ema50",
      "rsi_bucket": "neutral_40_50",
      "btc_regime": "mild_btc_up"
    },
    "raw_matching_cases": 26,
    "deduped_matching_cases": 17,
    "dedupe_gap_bars": 12,
    "dedupe_gap_minutes": 60,
    "decision": {
      "side": "LONG",
      "worth_trading": false,
      "reliability_grade": "D",
      "long_winrate_4h_pct": 58.82,
      "short_winrate_4h_pct": 41.18,
      "avg_4h_pct": 0.34623,
      "median_4h_pct": 0.32309,
      "long_tp1_before_sl_4h_all_cases_pct": 52.94,
      "short_tp1_before_sl_4h_all_cases_pct": 29.41,
      "reason": "Per mažai panašių atvejų. Net jei procentas geras, patikimumas silpnas."
    },
    "outcome_stats": {
      "cases": 17,
      "direction": {
        "15m": {
          "valid_cases": 17,
          "long_winrate_pct": 64.71,
          "short_winrate_pct": 35.29,
          "flat_cases_pct": 0.0
        },
        "1h": {
          "valid_cases": 17,
          "long_winrate_pct": 52.94,
          "short_winrate_pct": 47.06,
          "flat_cases_pct": 0.0
        },
        "4h": {
          "valid_cases": 17,
          "long_winrate_pct": 58.82,
          "short_winrate_pct": 41.18,
          "flat_cases_pct": 0.0
        }
      },
      "returns": {
        "15m": {
          "average_pct": 0.21774,
          "median_pct": 0.13474,
          "best_pct": 1.21831,
          "worst_pct": -0.38262
        },
        "1h": {
          "average_pct": -0.01601,
          "median_pct": 0.0112,
          "best_pct": 1.87075,
          "worst_pct": -2.258
        },
        "4h": {
          "average_pct": 0.34623,
          "median_pct": 0.32309,
          "best_pct": 4.69083,
          "worst_pct": -6.08288
        }
      },
      "risk": {
        "15m": {
          "long_avg_mfe_pct": 0.42905,
          "long_avg_mae_pct": -0.2001,
          "long_median_mfe_pct": 0.25766,
          "long_median_mae_pct": -0.10995,
          "short_avg_mfe_pct": 0.2001,
          "short_avg_mae_pct": 0.42905
        },
        "1h": {
          "long_avg_mfe_pct": 0.71971,
          "long_avg_mae_pct": -0.69423,
          "long_median_mfe_pct": 0.53345,
          "long_median_mae_pct": -0.37525,
          "short_avg_mfe_pct": 0.69423,
          "short_avg_mae_pct": 0.71971
        },
        "4h": {
          "long_avg_mfe_pct": 1.79284,
          "long_avg_mae_pct": -1.39531,
          "long_median_mfe_pct": 1.41845,
          "long_median_mae_pct": -0.46256,
          "short_avg_mfe_pct": 1.39531,
          "short_avg_mae_pct": 1.79284
        }
      },
      "tp_sl": {
        "long_tp1_before_sl_15m": {
          "available": true,
          "valid_sequence_cases": 2,
          "success_all_cases_pct": 11.76,
          "success_when_decided_pct": 100.0
        },
        "long_tp2_before_sl_15m": {
          "available": true,
          "valid_sequence_cases": 0,
          "success_all_cases_pct": 0.0,
          "success_when_decided_pct": null
        },
        "short_tp1_before_sl_15m": {
          "available": true,
          "valid_sequence_cases": 2,
          "success_all_cases_pct": 0.0,
          "success_when_decided_pct": 0.0
        },
        "short_tp2_before_sl_15m": {
          "available": true,
          "valid_sequence_cases": 2,
          "success_all_cases_pct": 0.0,
          "success_when_decided_pct": 0.0
        },
        "long_tp1_before_sl_1h": {
          "available": true,
          "valid_sequence_cases": 8,
          "success_all_cases_pct": 23.53,
          "success_when_decided_pct": 50.0
        },
        "long_tp2_before_sl_1h": {
          "available": true,
          "valid_sequence_cases": 6,
          "success_all_cases_pct": 11.76,
          "success_when_decided_pct": 33.33
        },
        "short_tp1_before_sl_1h": {
          "available": true,
          "valid_sequence_cases": 6,
          "success_all_cases_pct": 23.53,
          "success_when_decided_pct": 66.67
        },
        "short_tp2_before_sl_1h": {
          "available": true,
          "valid_sequence_cases": 4,
          "success_all_cases_pct": 11.76,
          "success_when_decided_pct": 50.0
        },
        "long_tp1_before_sl_4h": {
          "available": true,
          "valid_sequence_cases": 13,
          "success_all_cases_pct": 52.94,
          "success_when_decided_pct": 69.23
        },
        "long_tp2_before_sl_4h": {
          "available": true,
          "valid_sequence_cases": 10,
          "success_all_cases_pct": 35.29,
          "success_when_decided_pct": 60.0
        },
        "short_tp1_before_sl_4h": {
          "available": true,
          "valid_sequence_cases": 11,
          "success_all_cases_pct": 29.41,
          "success_when_decided_pct": 45.45
        },
        "short_tp2_before_sl_4h": {
          "available": true,
          "valid_sequence_cases": 10,
          "success_all_cases_pct": 23.53,
          "success_when_decided_pct": 40.0
        }
      }
    }
  },
  "recent_signal_stats": {
    "available": true,
    "cases": 27,
    "requested_limit": 30,
    "winrate_15m_pct": 48.15,
    "avg_side_return_15m_pct": 0.04545,
    "winrate_1h_pct": 62.96,
    "avg_side_return_1h_pct": 0.04576,
    "winrate_4h_pct": 66.67,
    "avg_side_return_4h_pct": 0.23524,
    "tp1_before_sl_4h_pct": 83.33,
    "tp2_before_sl_4h_pct": 50.0,
    "avg_mfe_4h_pct": 0.98033,
    "avg_mae_4h_pct": -0.64436,
    "by_grade": {
      "B+": {
        "cases": 1,
        "winrate_4h_pct": 0.0
      },
      "B": {
        "cases": 3,
        "winrate_4h_pct": 66.67
      },
      "UNKNOWN": {
        "cases": 23,
        "winrate_4h_pct": 69.57
      }
    }
  },
  "latest_features": {
    "return_1": 0.00017293,
    "return_3": -0.00418279,
    "return_12": -0.00104645,
    "ema20_dist": -0.00202739,
    "ema50_dist": 0.00064162,
    "ema200_dist": 0.01690633,
    "rsi14": 46.58330987,
    "atr_pct": 0.00320482,
    "macd": 0.35445334,
    "macd_signal": 0.99654345,
    "macd_hist": -0.64209011,
    "bb_pos": 0.11463173,
    "volume_ratio": 4.07120851,
    "range_pct": 0.00173913,
    "body_pct": 0.00017293,
    "adx14": 9.01266135,
    "bb_width": 0.00749452,
    "upper_wick_pct": 0.0009255,
    "lower_wick_pct": 0.00064073,
    "vwap20_dist": -0.00126984,
    "btc_return_1": 0.00096446,
    "btc_return_3": 0.00067896,
    "btc_return_12": 0.00206765,
    "btc_ema20_dist": 0.00033804,
    "eth_return_1": 0.0014015,
    "eth_return_3": 0.00087682,
    "eth_return_12": 0.00297887,
    "eth_ema20_dist": 0.00126704,
    "rel_btc_return_1": -0.00079154,
    "rel_btc_return_3": -0.00486175,
    "rel_btc_return_12": -0.0031141,
    "rel_eth_return_12": -0.00402532,
    "snapshot_available": 1.0,
    "bos_up_20": 0.0,
    "bos_down_20": 0.0,
    "liquidity_sweep_high_20": 0.0,
    "liquidity_sweep_low_20": 0.0,
    "fvg_up": 0.0,
    "fvg_down": 1.0,
    "fvg_up_gap_pct": 0.0,
    "fvg_down_gap_pct": 0.00032545,
    "rsi_bucket": "neutral_40_50",
    "trend_regime": "pullback_above_ema50",
    "volume_regime": "volume_spike",
    "btc_regime": "mild_btc_up",
    "eth_regime": "mild_eth_up",
    "oi_regime": "mild_oi_rising",
    "funding_regime": "neutral",
    "taker_regime": "strong_sell_pressure",
    "book_regime": "strong_bid_wall",
    "structure_regime": "fvg_down"
  },
  "market_context": {
    "MUUSDT": {
      "available": true,
      "symbol": "MUUSDT",
      "snapshot_count_loaded": 30,
      "latest": {
        "collected_at_utc": "2026-07-14T18:34:04.954000+00:00",
        "collected_at_ms": 1784054044954,
        "prices": {
          "last": 983.5,
          "mark": 983.38,
          "index": 983.23,
          "bid1": 983.34,
          "ask1": 983.41,
          "mid": 983.375,
          "spread_abs": 0.07,
          "spread_pct": 0.007118
        },
        "market_24h": {
          "price_change_pct": 5.9965,
          "high": 995.45,
          "low": 911.1,
          "volume": 44077.92,
          "turnover": 42245343.1132
        },
        "open_interest": {
          "ticker_open_interest": 15040.58,
          "ticker_open_interest_value": 14790605.56,
          "latest": 14989.42,
          "previous_interval": 14857.32,
          "interval_change_pct": 0.889124
        },
        "funding": {
          "rate": 0.0,
          "rate_pct": 0.0,
          "next_funding_time_ms": 1784073600000
        },
        "positioning": {
          "long_ratio": 0.5983,
          "short_ratio": 0.4017,
          "long_short_ratio": 1.48942,
          "long_ratio_change": 0.0011
        },
        "taker_flow": {
          "buy_volume": 199.0,
          "sell_volume": 464.47,
          "total_volume": 663.47,
          "buy_ratio": 0.299938,
          "sell_ratio": 0.700062,
          "delta": -265.47,
          "delta_ratio": -0.400124,
          "trades_count": 1000
        },
        "orderbook": {
          "top5": {
            "bid_qty": 2.23,
            "ask_qty": 1.68,
            "imbalance": 0.140665
          },
          "top10": {
            "bid_qty": 3.74,
            "ask_qty": 2.72,
            "imbalance": 0.157895,
            "bid_notional": 3677.4271,
            "ask_notional": 2675.1613,
            "notional_imbalance": 0.157773
          },
          "top25": {
            "bid_qty": 7.34,
            "ask_qty": 23.66,
            "imbalance": -0.526452
          }
        },
        "data_quality": {
          "ticker_ok": true,
          "orderbook_ok": true,
          "open_interest_ok": true,
          "long_short_ok": true,
          "funding_ok": true,
          "trades_ok": true
        }
      },
      "changes": {
        "from_previous_snapshot": {
          "comparison_snapshot_utc": "2026-07-14T18:18:50.791000+00:00",
          "elapsed_minutes": 15.24,
          "price_change_pct": -0.322293,
          "open_interest_change_pct": 0.813805,
          "ticker_oi_value_change_pct": 0.832349,
          "funding_rate_change": 0.0,
          "long_short_ratio_change": -0.03583256,
          "taker_delta_ratio_change": -0.30608944,
          "book_top10_imbalance_change": 0.00097166
        },
        "approximately_15m": {
          "comparison_snapshot_utc": "2026-07-14T18:18:50.791000+00:00",
          "elapsed_minutes": 15.24,
          "price_change_pct": -0.322293,
          "open_interest_change_pct": 0.813805,
          "ticker_oi_value_change_pct": 0.832349,
          "funding_rate_change": 0.0,
          "long_short_ratio_change": -0.03583256,
          "taker_delta_ratio_change": -0.30608944,
          "book_top10_imbalance_change": 0.00097166
        },
        "approximately_1h": {
          "comparison_snapshot_utc": "2026-07-14T18:18:50.791000+00:00",
          "elapsed_minutes": 15.24,
          "price_change_pct": -0.322293,
          "open_interest_change_pct": 0.813805,
          "ticker_oi_value_change_pct": 0.832349,
          "funding_rate_change": 0.0,
          "long_short_ratio_change": -0.03583256,
          "taker_delta_ratio_change": -0.30608944,
          "book_top10_imbalance_change": 0.00097166
        }
      }
    },
    "BTCUSDT": {
      "available": true,
      "symbol": "BTCUSDT",
      "snapshot_count_loaded": 30,
      "latest": {
        "collected_at_utc": "2026-07-14T18:34:07.442000+00:00",
        "collected_at_ms": 1784054047442,
        "prices": {
          "last": 64542.1,
          "mark": 64550.39,
          "index": 64571.93,
          "bid1": 64542.1,
          "ask1": 64542.2,
          "mid": 64542.15,
          "spread_abs": 0.1,
          "spread_pct": 0.000155
        },
        "market_24h": {
          "price_change_pct": 4.242,
          "high": 65000.0,
          "low": 61848.0,
          "volume": 81209.1,
          "turnover": 5152408195.679
        },
        "open_interest": {
          "ticker_open_interest": 56479.562,
          "ticker_open_interest_value": 3645777754.13,
          "latest": 56481.76,
          "previous_interval": 56474.917,
          "interval_change_pct": 0.012117
        },
        "funding": {
          "rate": 0.0001,
          "rate_pct": 0.01,
          "next_funding_time_ms": 1784073600000
        },
        "positioning": {
          "long_ratio": 0.5652,
          "short_ratio": 0.4348,
          "long_short_ratio": 1.299908,
          "long_ratio_change": -0.0003
        },
        "taker_flow": {
          "buy_volume": 28.625,
          "sell_volume": 4.223,
          "total_volume": 32.848,
          "buy_ratio": 0.871438,
          "sell_ratio": 0.128562,
          "delta": 24.402,
          "delta_ratio": 0.742876,
          "trades_count": 1000
        },
        "orderbook": {
          "top5": {
            "bid_qty": 2.664,
            "ask_qty": 2.562,
            "imbalance": 0.019518
          },
          "top10": {
            "bid_qty": 3.378,
            "ask_qty": 2.625,
            "imbalance": 0.125437,
            "bid_notional": 218022.128,
            "ask_notional": 169423.4052,
            "notional_imbalance": 0.125434
          },
          "top25": {
            "bid_qty": 5.325,
            "ask_qty": 3.787,
            "imbalance": 0.168788
          }
        },
        "data_quality": {
          "ticker_ok": true,
          "orderbook_ok": true,
          "open_interest_ok": true,
          "long_short_ok": true,
          "funding_ok": true,
          "trades_ok": true
        }
      },
      "changes": {
        "from_previous_snapshot": {
          "comparison_snapshot_utc": "2026-07-14T18:18:53.266000+00:00",
          "elapsed_minutes": 15.24,
          "price_change_pct": 0.04976,
          "open_interest_change_pct": 0.121303,
          "ticker_oi_value_change_pct": 0.129707,
          "funding_rate_change": 0.0,
          "long_short_ratio_change": -0.00530177,
          "taker_delta_ratio_change": 0.26141911,
          "book_top10_imbalance_change": -0.62590784
        },
        "approximately_15m": {
          "comparison_snapshot_utc": "2026-07-14T18:18:53.266000+00:00",
          "elapsed_minutes": 15.24,
          "price_change_pct": 0.04976,
          "open_interest_change_pct": 0.121303,
          "ticker_oi_value_change_pct": 0.129707,
          "funding_rate_change": 0.0,
          "long_short_ratio_change": -0.00530177,
          "taker_delta_ratio_change": 0.26141911,
          "book_top10_imbalance_change": -0.62590784
        },
        "approximately_1h": {
          "comparison_snapshot_utc": "2026-07-14T18:18:53.266000+00:00",
          "elapsed_minutes": 15.24,
          "price_change_pct": 0.04976,
          "open_interest_change_pct": 0.121303,
          "ticker_oi_value_change_pct": 0.129707,
          "funding_rate_change": 0.0,
          "long_short_ratio_change": -0.00530177,
          "taker_delta_ratio_change": 0.26141911,
          "book_top10_imbalance_change": -0.62590784
        }
      }
    },
    "ETHUSDT": {
      "available": true,
      "symbol": "ETHUSDT",
      "snapshot_count_loaded": 30,
      "latest": {
        "collected_at_utc": "2026-07-14T18:34:10.301000+00:00",
        "collected_at_ms": 1784054050301,
        "prices": {
          "last": 1871.77,
          "mark": 1871.56,
          "index": 1872.27,
          "bid1": 1871.76,
          "ask1": 1871.77,
          "mid": 1871.765,
          "spread_abs": 0.01,
          "spread_pct": 0.000534
        },
        "market_24h": {
          "price_change_pct": 6.434,
          "high": 1888.0,
          "low": 1751.21,
          "volume": 1652762.04,
          "turnover": 3017195160.5651
        },
        "open_interest": {
          "ticker_open_interest": 870707.02,
          "ticker_open_interest_value": 1629580430.35,
          "latest": 872384.79,
          "previous_interval": 872531.73,
          "interval_change_pct": -0.016841
        },
        "funding": {
          "rate": 3.719e-05,
          "rate_pct": 0.003719,
          "next_funding_time_ms": 1784073600000
        },
        "positioning": {
          "long_ratio": 0.6644,
          "short_ratio": 0.3356,
          "long_short_ratio": 1.979738,
          "long_ratio_change": -0.0003
        },
        "taker_flow": {
          "buy_volume": 353.63,
          "sell_volume": 108.97,
          "total_volume": 462.6,
          "buy_ratio": 0.76444,
          "sell_ratio": 0.23556,
          "delta": 244.66,
          "delta_ratio": 0.52888,
          "trades_count": 1000
        },
        "orderbook": {
          "top5": {
            "bid_qty": 62.73,
            "ask_qty": 13.47,
            "imbalance": 0.646457
          },
          "top10": {
            "bid_qty": 82.8,
            "ask_qty": 27.44,
            "imbalance": 0.502177,
            "bid_notional": 154980.441,
            "ask_notional": 51362.4937,
            "notional_imbalance": 0.502164
          },
          "top25": {
            "bid_qty": 168.92,
            "ask_qty": 112.79,
            "imbalance": 0.199247
          }
        },
        "data_quality": {
          "ticker_ok": true,
          "orderbook_ok": true,
          "open_interest_ok": true,
          "long_short_ok": true,
          "funding_ok": true,
          "trades_ok": true
        }
      },
      "changes": {
        "from_previous_snapshot": {
          "comparison_snapshot_utc": "2026-07-14T18:18:56.276000+00:00",
          "elapsed_minutes": 15.23,
          "price_change_pct": 0.073246,
          "open_interest_change_pct": -0.051966,
          "ticker_oi_value_change_pct": -0.163463,
          "funding_rate_change": -4.67e-06,
          "long_short_ratio_change": -0.00712004,
          "taker_delta_ratio_change": 0.0537858,
          "book_top10_imbalance_change": -0.24081937
        },
        "approximately_15m": {
          "comparison_snapshot_utc": "2026-07-14T18:18:56.276000+00:00",
          "elapsed_minutes": 15.23,
          "price_change_pct": 0.073246,
          "open_interest_change_pct": -0.051966,
          "ticker_oi_value_change_pct": -0.163463,
          "funding_rate_change": -4.67e-06,
          "long_short_ratio_change": -0.00712004,
          "taker_delta_ratio_change": 0.0537858,
          "book_top10_imbalance_change": -0.24081937
        },
        "approximately_1h": {
          "comparison_snapshot_utc": "2026-07-14T18:18:56.276000+00:00",
          "elapsed_minutes": 15.23,
          "price_change_pct": 0.073246,
          "open_interest_change_pct": -0.051966,
          "ticker_oi_value_change_pct": -0.163463,
          "funding_rate_change": -4.67e-06,
          "long_short_ratio_change": -0.00712004,
          "taker_delta_ratio_change": 0.0537858,
          "book_top10_imbalance_change": -0.24081937
        }
      }
    }
  },
  "position_context": {
    "side": "LONG",
    "leverage": 3,
    "entry": 1164.0,
    "liquidation": 789.0,
    "current_close": 983.25,
    "move_needed_to_entry_pct": 18.3829,
    "distance_to_liquidation_pct": 24.6198,
    "note": "Čia tik matematinis pozicijos kontekstas. Galutinę rekomendaciją formuoja išorinė analizė."
  },
  "similar_cases": [
    {
      "time_utc": "2026-07-12T15:55:00+00:00",
      "start_time_ms": 1783871700000,
      "close": 982.13,
      "similarity_pct": 19.436,
      "distance": 4.145083,
      "future_return_15m_pct": 0.07636,
      "future_return_1h_pct": 0.06516,
      "future_return_4h_pct": 0.19651,
      "future_mfe_4h_pct": 0.25353,
      "future_mae_4h_pct": -0.20364,
      "long_tp1_before_sl_4h": null,
      "short_tp1_before_sl_4h": null,
      "rsi14": 49.148,
      "ema20_dist_pct": -0.00713,
      "ema50_dist_pct": 0.00804,
      "ema200_dist_pct": 0.1063,
      "atr_pct": 0.07622,
      "volume_ratio": 3.72423,
      "bb_pos": 0.47336,
      "macd_hist": 0.049536,
      "btc_return_12_pct": -0.03132,
      "snap_oi_change_pct": 0.00316,
      "snap_funding_rate_pct": 0.0,
      "snap_taker_delta_ratio": 0.33622,
      "snap_book_imbalance_top10": 0.051282,
      "rsi_bucket": "neutral_40_50",
      "trend_regime": "pullback_above_ema50",
      "volume_regime": "volume_spike",
      "btc_regime": "neutral",
      "eth_regime": "neutral",
      "oi_regime": "neutral",
      "funding_regime": "neutral",
      "taker_regime": "strong_buy_pressure",
      "book_regime": "mild_bid_wall",
      "structure_regime": "none"
    },
    {
      "time_utc": "2026-07-12T20:25:00+00:00",
      "start_time_ms": 1783887900000,
      "close": 982.8,
      "similarity_pct": 19.299,
      "distance": 4.181531,
      "future_return_15m_pct": 0.08852,
      "future_return_1h_pct": -0.22283,
      "future_return_4h_pct": -0.09259,
      "future_mfe_4h_pct": 0.70615,
      "future_mae_4h_pct": -1.7735,
      "long_tp1_before_sl_4h": 0.0,
      "short_tp1_before_sl_4h": 1.0,
      "rsi14": 49.147,
      "ema20_dist_pct": -0.02726,
      "ema50_dist_pct": 0.02471,
      "ema200_dist_pct": 0.11827,
      "atr_pct": 0.06301,
      "volume_ratio": 4.91679,
      "bb_pos": 0.45585,
      "macd_hist": -0.074826,
      "btc_return_12_pct": 0.00265,
      "snap_oi_change_pct": -0.00055,
      "snap_funding_rate_pct": 0.0,
      "snap_taker_delta_ratio": 0.025994,
      "snap_book_imbalance_top10": 0.208577,
      "rsi_bucket": "neutral_40_50",
      "trend_regime": "pullback_above_ema50",
      "volume_regime": "volume_spike",
      "btc_regime": "neutral",
      "eth_regime": "neutral",
      "oi_regime": "neutral",
      "funding_regime": "neutral",
      "taker_regime": "neutral",
      "book_regime": "strong_bid_wall",
      "structure_regime": "none"
    },
    {
      "time_utc": "2026-07-05T20:20:00+00:00",
      "start_time_ms": 1783282800000,
      "close": 1037.12,
      "similarity_pct": 17.937,
      "distance": 4.574996,
      "future_return_15m_pct": -3.06233,
      "future_return_1h_pct": -3.39594,
      "future_return_4h_pct": -2.81838,
      "future_mfe_4h_pct": 0.00579,
      "future_mae_4h_pct": -4.30326,
      "long_tp1_before_sl_4h": 0.0,
      "short_tp1_before_sl_4h": 1.0,
      "rsi14": 56.823,
      "ema20_dist_pct": 0.0448,
      "ema50_dist_pct": 0.1447,
      "ema200_dist_pct": 0.35254,
      "atr_pct": 0.09763,
      "volume_ratio": 3.74867,
      "bb_pos": 0.59543,
      "macd_hist": -0.005941,
      "btc_return_12_pct": -0.02773,
      "snap_oi_change_pct": -0.19612,
      "snap_funding_rate_pct": -0.013562,
      "snap_taker_delta_ratio": -0.36897,
      "snap_book_imbalance_top10": 0.336508,
      "rsi_bucket": "strong_50_60",
      "trend_regime": "bull_trend",
      "volume_regime": "volume_spike",
      "btc_regime": "neutral",
      "eth_regime": "neutral",
      "oi_regime": "neutral",
      "funding_regime": "strong_negative_funding",
      "taker_regime": "strong_sell_pressure",
      "book_regime": "strong_bid_wall",
      "structure_regime": "none"
    },
    {
      "time_utc": "2026-07-10T18:15:00+00:00",
      "start_time_ms": 1783707300000,
      "close": 989.54,
      "similarity_pct": 17.831,
      "distance": 4.608355,
      "future_return_15m_pct": 0.15664,
      "future_return_1h_pct": 0.12733,
      "future_return_4h_pct": -0.94185,
      "future_mfe_4h_pct": 0.58512,
      "future_mae_4h_pct": -1.31071,
      "long_tp1_before_sl_4h": null,
      "short_tp1_before_sl_4h": 1.0,
      "rsi14": 54.216,
      "ema20_dist_pct": 0.06216,
      "ema50_dist_pct": 0.61244,
      "ema200_dist_pct": 0.84537,
      "atr_pct": 0.42269,
      "volume_ratio": 1.07086,
      "bb_pos": 0.51993,
      "macd_hist": -0.634746,
      "btc_return_12_pct": -0.00626,
      "snap_oi_change_pct": -0.09163,
      "snap_funding_rate_pct": 0.0,
      "snap_taker_delta_ratio": -0.126454,
      "snap_book_imbalance_top10": -0.372168,
      "rsi_bucket": "strong_50_60",
      "trend_regime": "bull_trend",
      "volume_regime": "normal_volume",
      "btc_regime": "neutral",
      "eth_regime": "neutral",
      "oi_regime": "neutral",
      "funding_regime": "neutral",
      "taker_regime": "mild_sell_pressure",
      "book_regime": "strong_ask_wall",
      "structure_regime": "fvg_down"
    },
    {
      "time_utc": "2026-07-13T15:45:00+00:00",
      "start_time_ms": 1783957500000,
      "close": 931.72,
      "similarity_pct": 16.466,
      "distance": 5.073011,
      "future_return_15m_pct": -0.09016,
      "future_return_1h_pct": -0.57743,
      "future_return_4h_pct": 0.66222,
      "future_mfe_4h_pct": 0.80389,
      "future_mae_4h_pct": -1.16988,
      "long_tp1_before_sl_4h": null,
      "short_tp1_before_sl_4h": 1.0,
      "rsi14": 46.096,
      "ema20_dist_pct": -0.40293,
      "ema50_dist_pct": -0.10157,
      "ema200_dist_pct": -0.72071,
      "atr_pct": 0.59607,
      "volume_ratio": 0.62325,
      "bb_pos": 0.16832,
      "macd_hist": -0.963915,
      "btc_return_12_pct": -0.10781,
      "snap_oi_change_pct": 0.25543,
      "snap_funding_rate_pct": 0.0,
      "snap_taker_delta_ratio": -0.221085,
      "snap_book_imbalance_top10": -0.24,
      "rsi_bucket": "neutral_40_50",
      "trend_regime": "mixed",
      "volume_regime": "low_volume",
      "btc_regime": "neutral",
      "eth_regime": "neutral",
      "oi_regime": "mild_oi_rising",
      "funding_regime": "neutral",
      "taker_regime": "strong_sell_pressure",
      "book_regime": "strong_ask_wall",
      "structure_regime": "fvg_down"
    },
    {
      "time_utc": "2026-07-13T06:00:00+00:00",
      "start_time_ms": 1783922400000,
      "close": 925.86,
      "similarity_pct": 15.675,
      "distance": 5.379427,
      "future_return_15m_pct": -0.70637,
      "future_return_1h_pct": -0.8079,
      "future_return_4h_pct": 0.42231,
      "future_mfe_4h_pct": 0.8187,
      "future_mae_4h_pct": -1.32093,
      "long_tp1_before_sl_4h": null,
      "short_tp1_before_sl_4h": 1.0,
      "rsi14": 46.562,
      "ema20_dist_pct": -0.04413,
      "ema50_dist_pct": -0.76706,
      "ema200_dist_pct": -3.34385,
      "atr_pct": 0.43817,
      "volume_ratio": 1.9576,
      "bb_pos": 0.56306,
      "macd_hist": 0.620694,
      "btc_return_12_pct": 0.14047,
      "snap_oi_change_pct": -0.05247,
      "snap_funding_rate_pct": 0.0,
      "snap_taker_delta_ratio": 0.56323,
      "snap_book_imbalance_top10": 0.351351,
      "rsi_bucket": "neutral_40_50",
      "trend_regime": "bear_trend",
      "volume_regime": "high_volume",
      "btc_regime": "neutral",
      "eth_regime": "neutral",
      "oi_regime": "neutral",
      "funding_regime": "neutral",
      "taker_regime": "strong_buy_pressure",
      "book_regime": "strong_bid_wall",
      "structure_regime": "none"
    },
    {
      "time_utc": "2026-07-05T15:50:00+00:00",
      "start_time_ms": 1783266600000,
      "close": 1029.55,
      "similarity_pct": 15.594,
      "distance": 5.41289,
      "future_return_15m_pct": 0.42543,
      "future_return_1h_pct": 0.41474,
      "future_return_4h_pct": 0.66534,
      "future_mfe_4h_pct": 0.82075,
      "future_mae_4h_pct": -0.02331,
      "long_tp1_before_sl_4h": null,
      "short_tp1_before_sl_4h": null,
      "rsi14": 36.983,
      "ema20_dist_pct": -0.18527,
      "ema50_dist_pct": -0.29678,
      "ema200_dist_pct": -0.24525,
      "atr_pct": 0.16236,
      "volume_ratio": 0.7288,
      "bb_pos": 0.23967,
      "macd_hist": 0.026489,
      "btc_return_12_pct": 0.0295,
      "snap_oi_change_pct": 0.18587,
      "snap_funding_rate_pct": 0.352358,
      "snap_taker_delta_ratio": 0.233181,
      "snap_book_imbalance_top10": -0.1265,
      "rsi_bucket": "weak_30_40",
      "trend_regime": "mixed",
      "volume_regime": "normal_volume",
      "btc_regime": "neutral",
      "eth_regime": "mild_eth_up",
      "oi_regime": "neutral",
      "funding_regime": "strong_positive_funding",
      "taker_regime": "strong_buy_pressure",
      "book_regime": "mild_ask_wall",
      "structure_regime": "none"
    },
    {
      "time_utc": "2026-07-04T08:35:00+00:00",
      "start_time_ms": 1783154100000,
      "close": 1028.97,
      "similarity_pct": 15.25,
      "distance": 5.557205,
      "future_return_15m_pct": -0.16133,
      "future_return_1h_pct": 0.11468,
      "future_return_4h_pct": 0.08552,
      "future_mfe_4h_pct": 0.23907,
      "future_mae_4h_pct": -0.34209,
      "long_tp1_before_sl_4h": null,
      "short_tp1_before_sl_4h": null,
      "rsi14": 46.357,
      "ema20_dist_pct": -0.06805,
      "ema50_dist_pct": -0.04285,
      "ema200_dist_pct": 0.22308,
      "atr_pct": 0.14455,
      "volume_ratio": 1.83085,
      "bb_pos": 0.29473,
      "macd_hist": -0.126963,
      "btc_return_12_pct": 0.23246,
      "snap_oi_change_pct": null,
      "snap_funding_rate_pct": null,
      "snap_taker_delta_ratio": null,
      "snap_book_imbalance_top10": null,
      "rsi_bucket": "neutral_40_50",
      "trend_regime": "mixed",
      "volume_regime": "high_volume",
      "btc_regime": "mild_btc_up",
      "eth_regime": "mild_eth_up",
      "oi_regime": null,
      "funding_regime": null,
      "taker_regime": null,
      "book_regime": null,
      "structure_regime": "fvg_down"
    },
    {
      "time_utc": "2026-07-03T18:35:00+00:00",
      "start_time_ms": 1783103700000,
      "close": 1021.71,
      "similarity_pct": 15.015,
      "distance": 5.660022,
      "future_return_15m_pct": 0.03915,
      "future_return_1h_pct": 0.19967,
      "future_return_4h_pct": 0.72721,
      "future_mfe_4h_pct": 1.31838,
      "future_mae_4h_pct": -0.27894,
      "long_tp1_before_sl_4h": 1.0,
      "short_tp1_before_sl_4h": null,
      "rsi14": 43.894,
      "ema20_dist_pct": -0.18756,
      "ema50_dist_pct": -0.27897,
      "ema200_dist_pct": 0.37824,
      "atr_pct": 0.24074,
      "volume_ratio": 2.24103,
      "bb_pos": 0.31429,
      "macd_hist": -0.047977,
      "btc_return_12_pct": -0.01688,
      "snap_oi_change_pct": null,
      "snap_funding_rate_pct": null,
      "snap_taker_delta_ratio": null,
      "snap_book_imbalance_top10": null,
      "rsi_bucket": "neutral_40_50",
      "trend_regime": "mixed",
      "volume_regime": "volume_spike",
      "btc_regime": "neutral",
      "eth_regime": "neutral",
      "oi_regime": null,
      "funding_regime": null,
      "taker_regime": null,
      "book_regime": null,
      "structure_regime": "fvg_down"
    },
    {
      "time_utc": "2026-07-03T23:20:00+00:00",
      "start_time_ms": 1783120800000,
      "close": 1030.19,
      "similarity_pct": 14.853,
      "distance": 5.732639,
      "future_return_15m_pct": -0.14949,
      "future_return_1h_pct": -0.45914,
      "future_return_4h_pct": -0.14852,
      "future_mfe_4h_pct": 0.49214,
      "future_mae_4h_pct": -0.7387,
      "long_tp1_before_sl_4h": null,
      "short_tp1_before_sl_4h": null,
      "rsi14": 49.354,
      "ema20_dist_pct": -0.09814,
      "ema50_dist_pct": 0.1666,
      "ema200_dist_pct": 0.8193,
      "atr_pct": 0.20278,
      "volume_ratio": 1.93966,
      "bb_pos": 0.17226,
      "macd_hist": -0.343843,
      "btc_return_12_pct": -0.06114,
      "snap_oi_change_pct": null,
      "snap_funding_rate_pct": null,
      "snap_taker_delta_ratio": null,
      "snap_book_imbalance_top10": null,
      "rsi_bucket": "neutral_40_50",
      "trend_regime": "pullback_above_ema50",
      "volume_regime": "high_volume",
      "btc_regime": "neutral",
      "eth_regime": "neutral",
      "oi_regime": null,
      "funding_regime": null,
      "taker_regime": null,
      "book_regime": null,
      "structure_regime": "fvg_down"
    },
    {
      "time_utc": "2026-07-04T03:20:00+00:00",
      "start_time_ms": 1783135200000,
      "close": 1028.66,
      "similarity_pct": 14.459,
      "distance": 5.916201,
      "future_return_15m_pct": -0.22942,
      "future_return_1h_pct": -0.37233,
      "future_return_4h_pct": 0.25276,
      "future_mfe_4h_pct": 0.34705,
      "future_mae_4h_pct": -0.51134,
      "long_tp1_before_sl_4h": null,
      "short_tp1_before_sl_4h": null,
      "rsi14": 42.826,
      "ema20_dist_pct": -0.1657,
      "ema50_dist_pct": -0.10999,
      "ema200_dist_pct": 0.37911,
      "atr_pct": 0.20418,
      "volume_ratio": 0.93544,
      "bb_pos": 0.21564,
      "macd_hist": -0.235396,
      "btc_return_12_pct": 0.12393,
      "snap_oi_change_pct": null,
      "snap_funding_rate_pct": null,
      "snap_taker_delta_ratio": null,
      "snap_book_imbalance_top10": null,
      "rsi_bucket": "neutral_40_50",
      "trend_regime": "mixed",
      "volume_regime": "normal_volume",
      "btc_regime": "neutral",
      "eth_regime": "neutral",
      "oi_regime": null,
      "funding_regime": null,
      "taker_regime": null,
      "book_regime": null,
      "structure_regime": "fvg_down"
    },
    {
      "time_utc": "2026-07-05T04:30:00+00:00",
      "start_time_ms": 1783225800000,
      "close": 1032.38,
      "similarity_pct": 14.389,
      "distance": 5.949922,
      "future_return_15m_pct": 0.00387,
      "future_return_1h_pct": 0.03681,
      "future_return_4h_pct": -0.0988,
      "future_mfe_4h_pct": 0.21601,
      "future_mae_4h_pct": -0.58312,
      "long_tp1_before_sl_4h": null,
      "short_tp1_before_sl_4h": null,
      "rsi14": 41.512,
      "ema20_dist_pct": -0.17754,
      "ema50_dist_pct": -0.10214,
      "ema200_dist_pct": 0.14202,
      "atr_pct": 0.16658,
      "volume_ratio": 1.05924,
      "bb_pos": 0.2484,
      "macd_hist": -0.174183,
      "btc_return_12_pct": 0.34535,
      "snap_oi_change_pct": null,
      "snap_funding_rate_pct": null,
      "snap_taker_delta_ratio": null,
      "snap_book_imbalance_top10": null,
      "rsi_bucket": "neutral_40_50",
      "trend_regime": "mixed",
      "volume_regime": "normal_volume",
      "btc_regime": "mild_btc_up",
      "eth_regime": "mild_eth_up",
      "oi_regime": null,
      "funding_regime": null,
      "taker_regime": null,
      "book_regime": null,
      "structure_regime": "fvg_down"
    },
    {
      "time_utc": "2026-07-10T23:20:00+00:00",
      "start_time_ms": 1783725600000,
      "close": 978.63,
      "similarity_pct": 14.355,
      "distance": 5.966352,
      "future_return_15m_pct": 0.14204,
      "future_return_1h_pct": 0.25239,
      "future_return_4h_pct": 0.50172,
      "future_mfe_4h_pct": 0.5661,
      "future_mae_4h_pct": -0.13897,
      "long_tp1_before_sl_4h": null,
      "short_tp1_before_sl_4h": null,
      "rsi14": 42.235,
      "ema20_dist_pct": -0.07976,
      "ema50_dist_pct": -0.22829,
      "ema200_dist_pct": -0.30846,
      "atr_pct": 0.11209,
      "volume_ratio": 1.43758,
      "bb_pos": 0.29323,
      "macd_hist": 0.140074,
      "btc_return_12_pct": 0.15395,
      "snap_oi_change_pct": null,
      "snap_funding_rate_pct": null,
      "snap_taker_delta_ratio": null,
      "snap_book_imbalance_top10": null,
      "rsi_bucket": "neutral_40_50",
      "trend_regime": "bear_trend",
      "volume_regime": "high_volume",
      "btc_regime": "neutral",
      "eth_regime": "neutral",
      "oi_regime": null,
      "funding_regime": null,
      "taker_regime": null,
      "book_regime": null,
      "structure_regime": "fvg_down"
    },
    {
      "time_utc": "2026-07-03T07:40:00+00:00",
      "start_time_ms": 1783064400000,
      "close": 1008.65,
      "similarity_pct": 14.343,
      "distance": 5.972094,
      "future_return_15m_pct": -0.04759,
      "future_return_1h_pct": 0.8665,
      "future_return_4h_pct": 2.69767,
      "future_mfe_4h_pct": 3.06053,
      "future_mae_4h_pct": -0.06444,
      "long_tp1_before_sl_4h": 1.0,
      "short_tp1_before_sl_4h": 0.0,
      "rsi14": 43.865,
      "ema20_dist_pct": -0.39804,
      "ema50_dist_pct": -0.05442,
      "ema200_dist_pct": 0.83923,
      "atr_pct": 0.43069,
      "volume_ratio": 0.39707,
      "bb_pos": 0.0729,
      "macd_hist": -0.825748,
      "btc_return_12_pct": 0.30527,
      "snap_oi_change_pct": null,
      "snap_funding_rate_pct": null,
      "snap_taker_delta_ratio": null,
      "snap_book_imbalance_top10": null,
      "rsi_bucket": "neutral_40_50",
      "trend_regime": "mixed",
      "volume_regime": "low_volume",
      "btc_regime": "mild_btc_up",
      "eth_regime": "mild_eth_up",
      "oi_regime": null,
      "funding_regime": null,
      "taker_regime": null,
      "book_regime": null,
      "structure_regime": "fvg_down"
    },
    {
      "time_utc": "2026-07-14T12:00:00+00:00",
      "start_time_ms": 1784030400000,
      "close": 967.04,
      "similarity_pct": 14.138,
      "distance": 6.073007,
      "future_return_15m_pct": -0.10031,
      "future_return_1h_pct": 2.07334,
      "future_return_4h_pct": 1.28743,
      "future_mfe_4h_pct": 2.93783,
      "future_mae_4h_pct": -1.6142,
      "long_tp1_before_sl_4h": 1.0,
      "short_tp1_before_sl_4h": 0.0,
      "rsi14": 46.844,
      "ema20_dist_pct": -0.20806,
      "ema50_dist_pct": 0.09699,
      "ema200_dist_pct": 1.7595,
      "atr_pct": 0.37264,
      "volume_ratio": 1.28515,
      "bb_pos": 0.28924,
      "macd_hist": -0.312258,
      "btc_return_12_pct": 0.13906,
      "snap_oi_change_pct": null,
      "snap_funding_rate_pct": null,
      "snap_taker_delta_ratio": null,
      "snap_book_imbalance_top10": null,
      "rsi_bucket": "neutral_40_50",
      "trend_regime": "pullback_above_ema50",
      "volume_regime": "normal_volume",
      "btc_regime": "neutral",
      "eth_regime": "neutral",
      "oi_regime": null,
      "funding_regime": null,
      "taker_regime": null,
      "book_regime": null,
      "structure_regime": "fvg_down"
    },
    {
      "time_utc": "2026-07-11T18:40:00+00:00",
      "start_time_ms": 1783795200000,
      "close": 986.21,
      "similarity_pct": 14.136,
      "distance": 6.074256,
      "future_return_15m_pct": -0.02535,
      "future_return_1h_pct": 0.17339,
      "future_return_4h_pct": -0.37619,
      "future_mfe_4h_pct": 0.25147,
      "future_mae_4h_pct": -0.44412,
      "long_tp1_before_sl_4h": null,
      "short_tp1_before_sl_4h": null,
      "rsi14": 50.892,
      "ema20_dist_pct": -0.01095,
      "ema50_dist_pct": 0.04123,
      "ema200_dist_pct": 0.12202,
      "atr_pct": 0.08315,
      "volume_ratio": 3.12263,
      "bb_pos": 0.28964,
      "macd_hist": -0.145628,
      "btc_return_12_pct": -0.00155,
      "snap_oi_change_pct": null,
      "snap_funding_rate_pct": null,
      "snap_taker_delta_ratio": null,
      "snap_book_imbalance_top10": null,
      "rsi_bucket": "strong_50_60",
      "trend_regime": "pullback_above_ema50",
      "volume_regime": "volume_spike",
      "btc_regime": "neutral",
      "eth_regime": "neutral",
      "oi_regime": null,
      "funding_regime": null,
      "taker_regime": null,
      "book_regime": null,
      "structure_regime": "none"
    },
    {
      "time_utc": "2026-07-10T04:50:00+00:00",
      "start_time_ms": 1783659000000,
      "close": 988.83,
      "similarity_pct": 14.072,
      "distance": 6.106325,
      "future_return_15m_pct": -0.46216,
      "future_return_1h_pct": -0.99613,
      "future_return_4h_pct": -2.20766,
      "future_mfe_4h_pct": 0.06877,
      "future_mae_4h_pct": -2.95804,
      "long_tp1_before_sl_4h": 0.0,
      "short_tp1_before_sl_4h": 1.0,
      "rsi14": 42.677,
      "ema20_dist_pct": -0.23116,
      "ema50_dist_pct": -0.32055,
      "ema200_dist_pct": -0.4845,
      "atr_pct": 0.25419,
      "volume_ratio": 1.2148,
      "bb_pos": 0.12661,
      "macd_hist": -0.169829,
      "btc_return_12_pct": 0.27424,
      "snap_oi_change_pct": null,
      "snap_funding_rate_pct": null,
      "snap_taker_delta_ratio": null,
      "snap_book_imbalance_top10": null,
      "rsi_bucket": "neutral_40_50",
      "trend_regime": "bear_trend",
      "volume_regime": "normal_volume",
      "btc_regime": "mild_btc_up",
      "eth_regime": "neutral",
      "oi_regime": null,
      "funding_regime": null,
      "taker_regime": null,
      "book_regime": null,
      "structure_regime": "fvg_down"
    },
    {
      "time_utc": "2026-07-11T06:10:00+00:00",
      "start_time_ms": 1783750200000,
      "close": 983.13,
      "similarity_pct": 14.026,
      "distance": 6.129485,
      "future_return_15m_pct": 0.04069,
      "future_return_1h_pct": 0.26751,
      "future_return_4h_pct": 0.25836,
      "future_mfe_4h_pct": 0.75066,
      "future_mae_4h_pct": -0.03865,
      "long_tp1_before_sl_4h": null,
      "short_tp1_before_sl_4h": null,
      "rsi14": 49.544,
      "ema20_dist_pct": -0.01542,
      "ema50_dist_pct": 0.0276,
      "ema200_dist_pct": 0.10426,
      "atr_pct": 0.08033,
      "volume_ratio": 3.39549,
      "bb_pos": 0.41511,
      "macd_hist": -0.004661,
      "btc_return_12_pct": 0.02027,
      "snap_oi_change_pct": null,
      "snap_funding_rate_pct": null,
      "snap_taker_delta_ratio": null,
      "snap_book_imbalance_top10": null,
      "rsi_bucket": "neutral_40_50",
      "trend_regime": "pullback_above_ema50",
      "volume_regime": "volume_spike",
      "btc_regime": "neutral",
      "eth_regime": "neutral",
      "oi_regime": null,
      "funding_regime": null,
      "taker_regime": null,
      "book_regime": null,
      "structure_regime": "none"
    },
    {
      "time_utc": "2026-07-04T14:15:00+00:00",
      "start_time_ms": 1783174500000,
      "close": 1027.22,
      "similarity_pct": 14.007,
      "distance": 6.139279,
      "future_return_15m_pct": 0.0662,
      "future_return_1h_pct": 0.16452,
      "future_return_4h_pct": 0.1762,
      "future_mfe_4h_pct": 0.33488,
      "future_mae_4h_pct": -0.41958,
      "long_tp1_before_sl_4h": null,
      "short_tp1_before_sl_4h": null,
      "rsi14": 40.577,
      "ema20_dist_pct": -0.13464,
      "ema50_dist_pct": -0.15712,
      "ema200_dist_pct": -0.05235,
      "atr_pct": 0.13237,
      "volume_ratio": 0.8767,
      "bb_pos": 0.06424,
      "macd_hist": -0.187956,
      "btc_return_12_pct": -0.03958,
      "snap_oi_change_pct": null,
      "snap_funding_rate_pct": null,
      "snap_taker_delta_ratio": null,
      "snap_book_imbalance_top10": null,
      "rsi_bucket": "neutral_40_50",
      "trend_regime": "mixed",
      "volume_regime": "normal_volume",
      "btc_regime": "neutral",
      "eth_regime": "mild_eth_up",
      "oi_regime": null,
      "funding_regime": null,
      "taker_regime": null,
      "book_regime": null,
      "structure_regime": "fvg_down"
    },
    {
      "time_utc": "2026-07-11T14:05:00+00:00",
      "start_time_ms": 1783778700000,
      "close": 984.96,
      "similarity_pct": 13.994,
      "distance": 6.146092,
      "future_return_15m_pct": -0.08325,
      "future_return_1h_pct": -0.02132,
      "future_return_4h_pct": 0.16346,
      "future_mfe_4h_pct": 0.31981,
      "future_mae_4h_pct": -0.25788,
      "long_tp1_before_sl_4h": null,
      "short_tp1_before_sl_4h": null,
      "rsi14": 38.602,
      "ema20_dist_pct": -0.12862,
      "ema50_dist_pct": -0.16597,
      "ema200_dist_pct": 0.0118,
      "atr_pct": 0.09389,
      "volume_ratio": 0.91204,
      "bb_pos": 0.25066,
      "macd_hist": -0.084341,
      "btc_return_12_pct": 0.13855,
      "snap_oi_change_pct": null,
      "snap_funding_rate_pct": null,
      "snap_taker_delta_ratio": null,
      "snap_book_imbalance_top10": null,
      "rsi_bucket": "weak_30_40",
      "trend_regime": "mixed",
      "volume_regime": "normal_volume",
      "btc_regime": "neutral",
      "eth_regime": "mild_eth_up",
      "oi_regime": null,
      "funding_regime": null,
      "taker_regime": null,
      "book_regime": null,
      "structure_regime": "fvg_down"
    }
  ],
  "report_notes": {
    "position_recommendation_included": false,
    "news_analysis_included": false,
    "final_market_assessment_included": false,
    "signal_outcome_tracking_enabled": true,
    "purpose": "Pattern Scanner V2.2: nearest-neighbor + condition buckets + signal_log V2 + rolling evaluated-signal statistics."
  }
}